MANIFEST.in
README.rst
VERSION
setup.cfg
setup.py
japaneezu/__init__.py
japaneezu/conjugation.py
japaneezu/data.py
japaneezu/lang_core.py
japaneezu/main.py
japaneezu.egg-info/PKG-INFO
japaneezu.egg-info/SOURCES.txt
japaneezu.egg-info/dependency_links.txt
japaneezu.egg-info/entry_points.txt
japaneezu.egg-info/top_level.txt
japaneezu/ui/__init__.py
japaneezu/ui/main.py
japaneezu/ui/widgets.py
test/test_conjugations.py