Metadata-Version: 1.1
Name: japaneezu
Version: 0.0.1
Summary: A curses/console foreign language language study tool. (Currently limited to Japanese.)
Home-page: https://github.com/stnbu/japaneezu
Author: Mike Burr
Author-email: mburr@unintuitive.org
License: MIT
Download-URL: https://github.com/stnbu/japaneezu/archive/master.zip
Keywords: language,study,japanese,parsing
Platform: UNKNOWN
Classifier: Development Status :: 2 - Pre-Alpha
Classifier: Environment :: Console :: Curses
Classifier: License :: OSI Approved :: MIT License
Classifier: Natural Language :: Japanese
Classifier: Programming Language :: Python :: 2
Requires: urwid
Requires: urwid_utils
Provides: japaneezu
